gdcapiwrapper/__init__.py
gdcapiwrapper/enums.py
gdcapiwrapper/exceptions.py
gdcapiwrapper/util.py
gdcapiwrapper/tcga/__init__.py
gdcapiwrapper/tcga/tcga.py
gdcapiwrapper/tcia/__init__.py
gdcapiwrapper/tcia/tcia.py
gdc_api_wrapper-0.2.dist-info/LICENSE.txt
gdc_api_wrapper-0.2.dist-info/METADATA
gdc_api_wrapper-0.2.dist-info/WHEEL
gdc_api_wrapper-0.2.dist-info/top_level.txt
gdc_api_wrapper-0.2.dist-info/zip-safe
gdc_api_wrapper-0.2.dist-info/RECORD
