Metadata-Version: 2.1
Name: gdc-api-wrapper
Version: 0.2
Summary: A simple Python wrapper for the GDC Application Programming Interface
Home-page: https://github.com/histolab/gdc-api-wrapper
Author: E. Arbitrio
Maintainer: Histolab Developers
Maintainer-email: ernesto.arbitrio@gmail.com
License: UNKNOWN
Download-URL: https://github.com/histolab/gdc-api-wrapper
Platform: UNKNOWN
Classifier: Programming Language :: Python :: 3
Classifier: Programming Language :: Python :: 3.6
Classifier: Programming Language :: Python :: 3.7
Classifier: Programming Language :: Python :: 3.8
Classifier: License :: OSI Approved :: Apache Software License
Classifier: Operating System :: OS Independent
Classifier: Intended Audience :: Science/Research
Requires-Python: >=3.6
Requires-Dist: requests[security]
Requires-Dist: responses
Requires-Dist: tqdm
Provides-Extra: testing
Requires-Dist: pytest ; extra == 'testing'
Requires-Dist: pytest-xdist ; extra == 'testing'
Requires-Dist: coverage ; extra == 'testing'
Requires-Dist: pytest-cov ; extra == 'testing'
Requires-Dist: coveralls ; extra == 'testing'
